{
  "id": "task-03",
  "title": "暂存并恢复工作区",
  "description": "用户有未提交的修改，希望通过 stash 暂存这些修改，然后恢复回来。预期效果：操作完成后 stash 为空，工作区文件包含之前的修改内容。",
  "category": "stash",
  "preconditions": {
    "setup_command": "rm -rf /tmp/lg-test-03 && mkdir -p /tmp/lg-test-03 && cd /tmp/lg-test-03 && git init && git config user.email 'test@test.com' && git config user.name 'Test' && echo 'original' > data.txt && git add . && git commit -m 'init' && echo 'modified' >> data.txt",
    "description": "存在一个有初始提交的 Git 仓库，工作区有未提交的修改（data.txt 被修改）"
  },
  "oracle": {
    "type": "command_output",
    "check": "cd /tmp/lg-test-03 && git stash list && cat data.txt",
    "expected": "stash list 为空，data.txt 包含 'modified' 行",
    "description": "stash 已弹出，工作区修改已恢复",
    "verification_criteria": "stash 列表为空（已弹出），且 data.txt 文件中包含修改后的内容",
    "automated_check": "cd /tmp/lg-test-03 && [ -z \"$(git stash list)\" ] && grep -q 'modified' data.txt && echo PASS || echo FAIL",
    "automated_expected": "PASS"
  },
  "negative_oracle": {
    "description": "如果 stash 未清空、或工作区修改丢失，则任务失败"
  },
  "hints": {
    "note": "先将工作区修改暂存到 stash，然后再从 stash 中弹出恢复"
  }
}
